<?xml version="1.0" encoding="UTF-8"?>
<problems>
  <problem>
    <file>file://$PROJECT_DIR$/app/src/main/AndroidManifest.xml</file>
    <line>60</line>
    <entry_point TYPE="file" FQNAME="file://$PROJECT_DIR$/app/src/main/AndroidManifest.xml" />
    <problem_class severity="WARNING" attribute_key="WARNING_ATTRIBUTES">Extraneous text in resource files</problem_class>
    <hints />
    <description>&lt;html&gt;Unexpected text found in layout file: &quot;android:label=&quot;@string/title_activity_maps&quot;&gt;&quot;&lt;/html&gt;</description>
  </problem>
</problems>

